dedmap/__init__.py
dedmap/dedmap.py
dedmap-2.dist-info/LICENSE
dedmap-2.dist-info/METADATA
dedmap-2.dist-info/NOTICE.md
dedmap-2.dist-info/WHEEL
dedmap-2.dist-info/top_level.txt
dedmap-2.dist-info/RECORD
