Metadata-Version: 2.1
Name: dedmap
Version: 2
Summary: A Simple but Powerful cross-platform port scanning & and network automation tool.
Home-page: https://github.com/7Ragnarok7/DEDMAP
Author: Anurag Mondal
Author-email: 7Ragnarok7@pm.me
License: UNKNOWN
Project-URL: Website, https://7ragnarok7.github.io/DEDMAP/
Project-URL: Bug Tracker, https://github.com/7Ragnarok7/DEDMAP/issues
Platform: UNKNOWN
Classifier: Programming Language :: Python :: 3
Classifier: License :: OSI Approved :: GNU General Public License v3 (GPLv3)
Classifier: Operating System :: OS Independent
Requires-Python: >=3.6
License-File: LICENSE
License-File: NOTICE.md
